[
  {
    "rcv_code": "R_00x20y",
    "metric": "t20",
    "f_hz": 125,
    "target_val": 5.643971212346544,
    "predicted_val": 2.0311829623966124,
    "error": -3.612788249949932
  },
  {
    "rcv_code": "R_00x20y",
    "metric": "t20",
    "f_hz": 250,
    "target_val": 2.211440041572608,
    "predicted_val": 2.216744158359481,
    "error": 0.0053041167868728145
  },
  {
    "rcv_code": "R_00x20y",
    "metric": "t20",
    "f_hz": 500,
    "target_val": 2.1185543566886302,
    "predicted_val": 2.2105013357625483,
    "error": 0.09194697907391802
  },
  {
    "rcv_code": "R_00x20y",
    "metric": "t20",
    "f_hz": 1000,
    "target_val": 1.8779081891794835,
    "predicted_val": 2.082544516284694,
    "error": 0.2046363271052105
  },
  {
    "rcv_code": "R_00x20y",
    "metric": "t20",
    "f_hz": 2000,
    "target_val": 2.0188694891591314,
    "predicted_val": 2.0364838333584916,
    "error": 0.017614344199360144
  },
  {
    "rcv_code": "R_00x20y",
    "metric": "t20",
    "f_hz": 4000,
    "target_val": 1.7492404436901166,
    "predicted_val": 1.7577208675112124,
    "error": 0.008480423821095817
  },
  {
    "rcv_code": "R_00x20y",
    "metric": "t20",
    "f_hz": 8000,
    "target_val": 1.1546544929687,
    "predicted_val": 1.1963548825177346,
    "error": 0.041700389549034655
  },
  {
    "rcv_code": "R_15x40y",
    "metric": "t20",
    "f_hz": 125,
    "target_val": 5.24870473061876,
    "predicted_val": 2.25091473747955,
    "error": -2.99778999313921
  },
  {
    "rcv_code": "R_15x40y",
    "metric": "t20",
    "f_hz": 250,
    "target_val": 2.2362975029086773,
    "predicted_val": 2.24527969431245,
    "error": 0.008982191403772433
  },
  {
    "rcv_code": "R_15x40y",
    "metric": "t20",
    "f_hz": 500,
    "target_val": 2.04183443304955,
    "predicted_val": 2.2462530244549916,
    "error": 0.2044185914054415
  },
  {
    "rcv_code": "R_15x40y",
    "metric": "t20",
    "f_hz": 1000,
    "target_val": 1.8425500081023867,
    "predicted_val": 2.0922124695719755,
    "error": 0.24966246146958881
  },
  {
    "rcv_code": "R_15x40y",
    "metric": "t20",
    "f_hz": 2000,
    "target_val": 1.975355402317205,
    "predicted_val": 2.0518394861706133,
    "error": 0.07648408385340821
  },
  {
    "rcv_code": "R_15x40y",
    "metric": "t20",
    "f_hz": 4000,
    "target_val": 1.6921628899740322,
    "predicted_val": 1.8401741961458764,
    "error": 0.14801130617184421
  },
  {
    "rcv_code": "R_15x40y",
    "metric": "t20",
    "f_hz": 8000,
    "target_val": 1.1413500485963997,
    "predicted_val": 1.195673652362192,
    "error": 0.05432360376579237
  },
  {
    "rcv_code": "R_30x00y",
    "metric": "t20",
    "f_hz": 125,
    "target_val": 4.5181704440481925,
    "predicted_val": 1.9656039351072558,
    "error": -2.5525665089409366
  },
  {
    "rcv_code": "R_30x00y",
    "metric": "t20",
    "f_hz": 250,
    "target_val": 2.5270500732315675,
    "predicted_val": 2.4287654552396893,
    "error": -0.09828461799187815
  },
  {
    "rcv_code": "R_30x00y",
    "metric": "t20",
    "f_hz": 500,
    "target_val": 2.0474574192894757,
    "predicted_val": 2.242066306994405,
    "error": 0.19460888770492923
  },
  {
    "rcv_code": "R_30x00y",
    "metric": "t20",
    "f_hz": 1000,
    "target_val": 1.900576150470351,
    "predicted_val": 2.021620417421455,
    "error": 0.12104426695110426
  },
  {
    "rcv_code": "R_30x00y",
    "metric": "t20",
    "f_hz": 2000,
    "target_val": 1.9494637000876818,
    "predicted_val": 2.0336499317013073,
    "error": 0.08418623161362548
  },
  {
    "rcv_code": "R_30x00y",
    "metric": "t20",
    "f_hz": 4000,
    "target_val": 1.7283309144215306,
    "predicted_val": 1.8177292693402767,
    "error": 0.08939835491874604
  },
  {
    "rcv_code": "R_30x00y",
    "metric": "t20",
    "f_hz": 8000,
    "target_val": 1.1190407202398613,
    "predicted_val": 1.204062537162522,
    "error": 0.08502181692266064
  },
  {
    "rcv_code": "R_40x30y",
    "metric": "t20",
    "f_hz": 250,
    "target_val": 2.3088797109074415,
    "predicted_val": 2.1096896007516577,
    "error": -0.1991901101557838
  },
  {
    "rcv_code": "R_40x30y",
    "metric": "t20",
    "f_hz": 500,
    "target_val": 2.269310960562598,
    "predicted_val": 2.266728287334476,
    "error": -0.002582673228122001
  },
  {
    "rcv_code": "R_40x30y",
    "metric": "t20",
    "f_hz": 1000,
    "target_val": 1.906945453642093,
    "predicted_val": 2.183001889402746,
    "error": 0.2760564357606532
  },
  {
    "rcv_code": "R_40x30y",
    "metric": "t20",
    "f_hz": 2000,
    "target_val": 2.00015735657735,
    "predicted_val": 2.0527558247650104,
    "error": 0.05259846818766034
  },
  {
    "rcv_code": "R_40x30y",
    "metric": "t20",
    "f_hz": 4000,
    "target_val": 1.7134505406232012,
    "predicted_val": 1.7994232495047588,
    "error": 0.08597270888155761
  },
  {
    "rcv_code": "R_40x30y",
    "metric": "t20",
    "f_hz": 8000,
    "target_val": 1.1538209280348974,
    "predicted_val": 1.2123164316102868,
    "error": 0.05849550357538935
  },
  {
    "rcv_code": "R_60x15y",
    "metric": "t20",
    "f_hz": 125,
    "target_val": 6.203911889674429,
    "predicted_val": 2.138301132304215,
    "error": -4.065610757370214
  },
  {
    "rcv_code": "R_60x15y",
    "metric": "t20",
    "f_hz": 250,
    "target_val": 2.1605912368237647,
    "predicted_val": 2.1865862114294736,
    "error": 0.025994974605708876
  },
  {
    "rcv_code": "R_60x15y",
    "metric": "t20",
    "f_hz": 500,
    "target_val": 2.1601015400130805,
    "predicted_val": 2.177752211016479,
    "error": 0.017650671003398344
  },
  {
    "rcv_code": "R_60x15y",
    "metric": "t20",
    "f_hz": 1000,
    "target_val": 1.9201734173887237,
    "predicted_val": 2.1259022202911253,
    "error": 0.2057288029024016
  },
  {
    "rcv_code": "R_60x15y",
    "metric": "t20",
    "f_hz": 2000,
    "target_val": 2.0170344827541955,
    "predicted_val": 2.0630332047921764,
    "error": 0.045998722037980944
  },
  {
    "rcv_code": "R_60x15y",
    "metric": "t20",
    "f_hz": 4000,
    "target_val": 1.7365657787420206,
    "predicted_val": 1.7805995735283169,
    "error": 0.04403379478629632
  },
  {
    "rcv_code": "R_60x15y",
    "metric": "t20",
    "f_hz": 8000,
    "target_val": 1.1573123959465188,
    "predicted_val": 1.183243738553444,
    "error": 0.0259313426069252
  }
]